MANIFEST.in
README.rst
setup.py
Flask_Material_Lite.egg-info/PKG-INFO
Flask_Material_Lite.egg-info/SOURCES.txt
Flask_Material_Lite.egg-info/dependency_links.txt
Flask_Material_Lite.egg-info/not-zip-safe
Flask_Material_Lite.egg-info/requires.txt
Flask_Material_Lite.egg-info/top_level.txt
flask_material_lite/__init__.py