Metadata-Version: 1.1
Name: Flask-Material-Lite
Version: 0.0.1
Summary: An easy way to get started with Google's Material Lite in your next Flask project, without any boilerplate code.
Home-page: https://github.com/HellerCommaA/flask-material-lite
Author: Adam Heller
Author-email: heller@mailbox.org
License: MIT
Platform: any
Classifier: Environment :: Web Environment
Classifier: Intended Audience :: Developers
Classifier: License :: OSI Approved :: MIT License
Classifier: Operating System :: OS Independent
Classifier: Programming Language :: Python
Classifier: Programming Language :: Python :: 2
Classifier: Topic :: Internet :: WWW/HTTP :: Dynamic Content
Classifier: Topic :: Software Development :: Libraries :: Python Modules
